mszutils/__init__.py
mszutils/common.py
mszutils-1.0.2.dist-info/LICENSE
mszutils-1.0.2.dist-info/METADATA
mszutils-1.0.2.dist-info/WHEEL
mszutils-1.0.2.dist-info/top_level.txt
mszutils-1.0.2.dist-info/RECORD
