Metadata-Version: 2.1
Name: mszutils
Version: 1.0.2
Summary: Provide common used functionalities.
Author-email: Marcin Szydłowski <marcinszydlowski.python@gmail.com>
License: The MIT License (MIT)
Project-URL: Homepage, https://bitbucket.org
Keywords: utils
Classifier: License :: OSI Approved :: MIT License
Classifier: Programming Language :: Python :: 3
Requires-Python: >=3.10
License-File: LICENSE
Provides-Extra: dev
Requires-Dist: bumpver ; extra == 'dev'
Requires-Dist: pytest ; extra == 'dev'
